MANIFEST.in
README.rst
setup.cfg
setup.py
pep_quality/__init__.py
pep_quality/quality.py
pep_quality.egg-info/PKG-INFO
pep_quality.egg-info/SOURCES.txt
pep_quality.egg-info/dependency_links.txt
pep_quality.egg-info/requires.txt
pep_quality.egg-info/top_level.txt