Metadata-Version: 1.1
Name: pep-quality
Version: 1.4.0
Summary: PEP8 small quality test
Home-page: http://yazanpsut.github.io/pep-quality/
Author: Yazan Alhorani
Author-email: yazan_alhorani@hotmail.com
License: MIT
Download-URL: https://github.com/yazanpsut/pep-quality/zipball/master
Keywords: PEP8 PEP-quality code codestyle
Platform: UNKNOWN
Classifier: Development Status :: 3 - Alpha
Classifier: Intended Audience :: Developers
Classifier: Topic :: Software Development :: Build Tools
Classifier: License :: OSI Approved :: MIT License
Classifier: Programming Language :: Python :: 2.7
